{
  "zones": [
    {
      "id": "d41e0d73-62c8-40c0-b224-94d7921bfff9",
      "fabricObject": {
        "type": "Polygon",
        "version": "6.6.5",
        "originX": "left",
        "originY": "top",
        "left": 17.0242,
        "top": 41.4034,
        "width": 673,
        "height": 701,
        "fill": "rgba(30, 144, 255, 0.18)",
        "stroke": "#2196f3",
        "strokeWidth": 3,
        "strokeDashArray": [
          8,
          4
        ],
        "strokeLineCap": "butt",
        "strokeDashOffset": 0,
        "strokeLineJoin": "miter",
        "strokeUniform": false,
        "strokeMiterLimit": 4,
        "scaleX": 1,
        "scaleY": 1,
        "angle": 0,
        "flipX": false,
        "flipY": false,
        "opacity": 1,
        "shadow": {
          "color": "#90caf9",
          "blur": 14,
          "offsetX": 0,
          "offsetY": 2,
          "affectStroke": false,
          "nonScaling": false,
          "type": "shadow"
        },
        "visible": true,
        "backgroundColor": "",
        "fillRule": "nonzero",
        "paintFirst": "fill",
        "globalCompositeOperation": "source-over",
        "skewX": 0,
        "skewY": 0,
        "objectId": "d41e0d73-62c8-40c0-b224-94d7921bfff9",
        "objectType": "parkingZone",
        "points": [
          {
            "x": 18,
            "y": 68
          },
          {
            "x": 22,
            "y": 227
          },
          {
            "x": 397,
            "y": 749
          },
          {
            "x": 450,
            "y": 698
          },
          {
            "x": 104,
            "y": 204
          },
          {
            "x": 102,
            "y": 140
          },
          {
            "x": 640,
            "y": 142
          },
          {
            "x": 684,
            "y": 143
          },
          {
            "x": 691,
            "y": 143
          },
          {
            "x": 689,
            "y": 48
          }
        ]
      }
    },
    {
      "id": "999d19fa-016f-40e6-ba11-f10f11081ba8",
      "fabricObject": {
        "type": "Polygon",
        "version": "6.6.5",
        "originX": "left",
        "originY": "top",
        "left": 666.5,
        "top": 154.5,
        "width": 101,
        "height": 565,
        "fill": "rgba(30, 144, 255, 0.18)",
        "stroke": "#2196f3",
        "strokeWidth": 3,
        "strokeDashArray": [
          8,
          4
        ],
        "strokeLineCap": "butt",
        "strokeDashOffset": 0,
        "strokeLineJoin": "miter",
        "strokeUniform": false,
        "strokeMiterLimit": 4,
        "scaleX": 1,
        "scaleY": 1,
        "angle": 0,
        "flipX": false,
        "flipY": false,
        "opacity": 1,
        "shadow": {
          "color": "#90caf9",
          "blur": 14,
          "offsetX": 0,
          "offsetY": 2,
          "affectStroke": false,
          "nonScaling": false,
          "type": "shadow"
        },
        "visible": true,
        "backgroundColor": "",
        "fillRule": "nonzero",
        "paintFirst": "fill",
        "globalCompositeOperation": "source-over",
        "skewX": 0,
        "skewY": 0,
        "objectId": "999d19fa-016f-40e6-ba11-f10f11081ba8",
        "objectType": "parkingZone",
        "points": [
          {
            "x": 744,
            "y": 157
          },
          {
            "x": 752,
            "y": 720
          },
          {
            "x": 845,
            "y": 719
          },
          {
            "x": 839,
            "y": 155
          }
        ]
      }
    }
  ],
  "obstacles": [
    {
      "id": "f3438694-92ef-4327-bc3c-638190a5f7b8",
      "type": "tree",
      "fabricObject": {
        "radius": 32,
        "startAngle": 0,
        "endAngle": 360,
        "counterClockwise": false,
        "type": "Circle",
        "version": "6.6.5",
        "originX": "left",
        "originY": "top",
        "left": 520,
        "top": 196,
        "width": 64,
        "height": 64,
        "fill": {
          "type": "radial",
          "coords": {
            "x1": 0.5,
            "y1": 0.5,
            "x2": 0.5,
            "y2": 0.5,
            "r1": 5,
            "r2": 32
          },
          "colorStops": [
            {
              "offset": 0,
              "color": "#a6e674"
            },
            {
              "offset": 1,
              "color": "#399f38"
            }
          ],
          "offsetX": 0,
          "offsetY": 0,
          "gradientUnits": "pixels"
        },
        "stroke": null,
        "strokeWidth": 1,
        "strokeDashArray": null,
        "strokeLineCap": "butt",
        "strokeDashOffset": 0,
        "strokeLineJoin": "miter",
        "strokeUniform": false,
        "strokeMiterLimit": 4,
        "scaleX": 1,
        "scaleY": 1,
        "angle": 0,
        "flipX": false,
        "flipY": false,
        "opacity": 1,
        "shadow": {
          "color": "#399f38",
          "blur": 12,
          "offsetX": 0,
          "offsetY": 4,
          "affectStroke": false,
          "nonScaling": false,
          "type": "shadow"
        },
        "visible": true,
        "backgroundColor": "",
        "fillRule": "nonzero",
        "paintFirst": "fill",
        "globalCompositeOperation": "source-over",
        "skewX": 0,
        "skewY": 0,
        "objectId": "eae453ea-f557-459c-8644-89816cd8b2db",
        "objectType": "obstacle"
      }
    },
    {
      "id": "6517d99f-0175-45af-bc18-aa328f055c2d",
      "type": "tree",
      "fabricObject": {
        "radius": 32,
        "startAngle": 0,
        "endAngle": 360,
        "counterClockwise": false,
        "type": "Circle",
        "version": "6.6.5",
        "originX": "left",
        "originY": "top",
        "left": 291,
        "top": 193,
        "width": 64,
        "height": 64,
        "fill": {
          "type": "radial",
          "coords": {
            "x1": 0.5,
            "y1": 0.5,
            "x2": 0.5,
            "y2": 0.5,
            "r1": 5,
            "r2": 32
          },
          "colorStops": [
            {
              "offset": 0,
              "color": "#a6e674"
            },
            {
              "offset": 1,
              "color": "#399f38"
            }
          ],
          "offsetX": 0,
          "offsetY": 0,
          "gradientUnits": "pixels"
        },
        "stroke": null,
        "strokeWidth": 1,
        "strokeDashArray": null,
        "strokeLineCap": "butt",
        "strokeDashOffset": 0,
        "strokeLineJoin": "miter",
        "strokeUniform": false,
        "strokeMiterLimit": 4,
        "scaleX": 1,
        "scaleY": 1,
        "angle": 0,
        "flipX": false,
        "flipY": false,
        "opacity": 1,
        "shadow": {
          "color": "#399f38",
          "blur": 12,
          "offsetX": 0,
          "offsetY": 4,
          "affectStroke": false,
          "nonScaling": false,
          "type": "shadow"
        },
        "visible": true,
        "backgroundColor": "",
        "fillRule": "nonzero",
        "paintFirst": "fill",
        "globalCompositeOperation": "source-over",
        "skewX": 0,
        "skewY": 0,
        "objectId": "ab66d501-dfe7-4dd6-a7a8-c2f69ecc3297",
        "objectType": "obstacle"
      }
    },
    {
      "id": "8f20d37c-04b8-47aa-b128-f88ec3c2d681",
      "type": "tree",
      "fabricObject": {
        "radius": 32,
        "startAngle": 0,
        "endAngle": 360,
        "counterClockwise": false,
        "type": "Circle",
        "version": "6.6.5",
        "originX": "left",
        "originY": "top",
        "left": 454,
        "top": 409,
        "width": 64,
        "height": 64,
        "fill": {
          "type": "radial",
          "coords": {
            "x1": 0.5,
            "y1": 0.5,
            "x2": 0.5,
            "y2": 0.5,
            "r1": 5,
            "r2": 32
          },
          "colorStops": [
            {
              "offset": 0,
              "color": "#a6e674"
            },
            {
              "offset": 1,
              "color": "#399f38"
            }
          ],
          "offsetX": 0,
          "offsetY": 0,
          "gradientUnits": "pixels"
        },
        "stroke": null,
        "strokeWidth": 1,
        "strokeDashArray": null,
        "strokeLineCap": "butt",
        "strokeDashOffset": 0,
        "strokeLineJoin": "miter",
        "strokeUniform": false,
        "strokeMiterLimit": 4,
        "scaleX": 1,
        "scaleY": 1,
        "angle": 0,
        "flipX": false,
        "flipY": false,
        "opacity": 1,
        "shadow": {
          "color": "#399f38",
          "blur": 12,
          "offsetX": 0,
          "offsetY": 4,
          "affectStroke": false,
          "nonScaling": false,
          "type": "shadow"
        },
        "visible": true,
        "backgroundColor": "",
        "fillRule": "nonzero",
        "paintFirst": "fill",
        "globalCompositeOperation": "source-over",
        "skewX": 0,
        "skewY": 0,
        "objectId": "07452613-b9b4-4297-8580-ad50ca67c0f5",
        "objectType": "obstacle"
      }
    },
    {
      "id": "fac04e37-61a0-4385-86cf-e426a9f28507",
      "type": "tree",
      "fabricObject": {
        "radius": 32,
        "startAngle": 0,
        "endAngle": 360,
        "counterClockwise": false,
        "type": "Circle",
        "version": "6.6.5",
        "originX": "left",
        "originY": "top",
        "left": 558,
        "top": 674,
        "width": 64,
        "height": 64,
        "fill": {
          "type": "radial",
          "coords": {
            "x1": 0.5,
            "y1": 0.5,
            "x2": 0.5,
            "y2": 0.5,
            "r1": 5,
            "r2": 32
          },
          "colorStops": [
            {
              "offset": 0,
              "color": "#a6e674"
            },
            {
              "offset": 1,
              "color": "#399f38"
            }
          ],
          "offsetX": 0,
          "offsetY": 0,
          "gradientUnits": "pixels"
        },
        "stroke": null,
        "strokeWidth": 1,
        "strokeDashArray": null,
        "strokeLineCap": "butt",
        "strokeDashOffset": 0,
        "strokeLineJoin": "miter",
        "strokeUniform": false,
        "strokeMiterLimit": 4,
        "scaleX": 1,
        "scaleY": 1,
        "angle": 0,
        "flipX": false,
        "flipY": false,
        "opacity": 1,
        "shadow": {
          "color": "#399f38",
          "blur": 12,
          "offsetX": 0,
          "offsetY": 4,
          "affectStroke": false,
          "nonScaling": false,
          "type": "shadow"
        },
        "visible": true,
        "backgroundColor": "",
        "fillRule": "nonzero",
        "paintFirst": "fill",
        "globalCompositeOperation": "source-over",
        "skewX": 0,
        "skewY": 0,
        "objectId": "be16f975-4080-42e7-85e4-4fc716894377",
        "objectType": "obstacle"
      }
    },
    {
      "id": "40574a7a-ffef-47b8-a274-16b799968ef2",
      "type": "tree",
      "fabricObject": {
        "radius": 32,
        "startAngle": 0,
        "endAngle": 360,
        "counterClockwise": false,
        "type": "Circle",
        "version": "6.6.5",
        "originX": "left",
        "originY": "top",
        "left": 43,
        "top": 468,
        "width": 64,
        "height": 64,
        "fill": {
          "type": "radial",
          "coords": {
            "x1": 0.5,
            "y1": 0.5,
            "x2": 0.5,
            "y2": 0.5,
            "r1": 5,
            "r2": 32
          },
          "colorStops": [
            {
              "offset": 0,
              "color": "#a6e674"
            },
            {
              "offset": 1,
              "color": "#399f38"
            }
          ],
          "offsetX": 0,
          "offsetY": 0,
          "gradientUnits": "pixels"
        },
        "stroke": null,
        "strokeWidth": 1,
        "strokeDashArray": null,
        "strokeLineCap": "butt",
        "strokeDashOffset": 0,
        "strokeLineJoin": "miter",
        "strokeUniform": false,
        "strokeMiterLimit": 4,
        "scaleX": 1,
        "scaleY": 1,
        "angle": 0,
        "flipX": false,
        "flipY": false,
        "opacity": 1,
        "shadow": {
          "color": "#399f38",
          "blur": 12,
          "offsetX": 0,
          "offsetY": 4,
          "affectStroke": false,
          "nonScaling": false,
          "type": "shadow"
        },
        "visible": true,
        "backgroundColor": "",
        "fillRule": "nonzero",
        "paintFirst": "fill",
        "globalCompositeOperation": "source-over",
        "skewX": 0,
        "skewY": 0,
        "objectId": "d1ec7207-217b-4782-be1c-bc7b15018d39",
        "objectType": "obstacle"
      }
    },
    {
      "id": "b929243b-32c6-4bc0-b922-7fa33ec0dcf9",
      "type": "tree",
      "fabricObject": {
        "radius": 32,
        "startAngle": 0,
        "endAngle": 360,
        "counterClockwise": false,
        "type": "Circle",
        "version": "6.6.5",
        "originX": "left",
        "originY": "top",
        "left": 308,
        "top": 711,
        "width": 64,
        "height": 64,
        "fill": {
          "type": "radial",
          "coords": {
            "x1": 0.5,
            "y1": 0.5,
            "x2": 0.5,
            "y2": 0.5,
            "r1": 5,
            "r2": 32
          },
          "colorStops": [
            {
              "offset": 0,
              "color": "#a6e674"
            },
            {
              "offset": 1,
              "color": "#399f38"
            }
          ],
          "offsetX": 0,
          "offsetY": 0,
          "gradientUnits": "pixels"
        },
        "stroke": null,
        "strokeWidth": 1,
        "strokeDashArray": null,
        "strokeLineCap": "butt",
        "strokeDashOffset": 0,
        "strokeLineJoin": "miter",
        "strokeUniform": false,
        "strokeMiterLimit": 4,
        "scaleX": 1,
        "scaleY": 1,
        "angle": 0,
        "flipX": false,
        "flipY": false,
        "opacity": 1,
        "shadow": {
          "color": "#399f38",
          "blur": 12,
          "offsetX": 0,
          "offsetY": 4,
          "affectStroke": false,
          "nonScaling": false,
          "type": "shadow"
        },
        "visible": true,
        "backgroundColor": "",
        "fillRule": "nonzero",
        "paintFirst": "fill",
        "globalCompositeOperation": "source-over",
        "skewX": 0,
        "skewY": 0,
        "objectId": "4c130522-85e2-4776-ba82-cf64c4f3a9e9",
        "objectType": "obstacle"
      }
    }
  ],
  "spotGroups": [
    {
      "id": "4205b7dc-7a8e-44c3-bcde-623e2884f8b5",
      "line": {
        "type": "Line",
        "version": "6.6.5",
        "originX": "left",
        "originY": "top",
        "left": 40,
        "top": 91,
        "width": 701,
        "height": 3,
        "fill": "rgb(0,0,0)",
        "stroke": "#1976d2",
        "strokeWidth": 4,
        "strokeDashArray": null,
        "strokeLineCap": "round",
        "strokeDashOffset": 0,
        "strokeLineJoin": "miter",
        "strokeUniform": false,
        "strokeMiterLimit": 4,
        "scaleX": 1,
        "scaleY": 1,
        "angle": 0,
        "flipX": false,
        "flipY": false,
        "opacity": 1,
        "shadow": {
          "color": "#a2c8f7",
          "blur": 8,
          "offsetX": 0,
          "offsetY": 2,
          "affectStroke": false,
          "nonScaling": false,
          "type": "shadow"
        },
        "visible": true,
        "backgroundColor": "",
        "fillRule": "nonzero",
        "paintFirst": "fill",
        "globalCompositeOperation": "source-over",
        "skewX": 0,
        "skewY": 0,
        "objectId": "4205b7dc-7a8e-44c3-bcde-623e2884f8b5",
        "groupId": "4205b7dc-7a8e-44c3-bcde-623e2884f8b5",
        "objectType": "parkingGroup",
        "x1": -350.5,
        "x2": 350.5,
        "y1": 1.5,
        "y2": -1.5
      },
      "spots": [
        {
          "rx": 8,
          "ry": 8,
          "type": "Rect",
          "version": "6.6.5",
          "originX": "center",
          "originY": "center",
          "left": 119.8889,
          "top": 95.6667,
          "width": 40,
          "height": 60,
          "fill": "#f7f7fa",
          "stroke": "#1890ff",
          "strokeWidth": 2.5,
          "strokeDashArray": null,
          "strokeLineCap": "butt",
          "strokeDashOffset": 0,
          "strokeLineJoin": "miter",
          "strokeUniform": true,
          "strokeMiterLimit": 4,
          "scaleX": 1,
          "scaleY": 1,
          "angle": 0,
          "flipX": false,
          "flipY": false,
          "opacity": 1,
          "shadow": {
            "color": "#cbe8ff",
            "blur": 8,
            "offsetX": 0,
            "offsetY": 2,
            "affectStroke": false,
            "nonScaling": false,
            "type": "shadow"
          },
          "visible": true,
          "backgroundColor": "",
          "fillRule": "nonzero",
          "paintFirst": "fill",
          "globalCompositeOperation": "source-over",
          "skewX": 0,
          "skewY": 0,
          "groupId": "4205b7dc-7a8e-44c3-bcde-623e2884f8b5",
          "objectType": "parkingGroup",
          "spotId": "82d3d324-6e40-4e46-b3b3-3acd0dd0c359"
        },
        {
          "rx": 8,
          "ry": 8,
          "type": "Rect",
          "version": "6.6.5",
          "originX": "center",
          "originY": "center",
          "left": 197.7778,
          "top": 95.3333,
          "width": 40,
          "height": 60,
          "fill": "#f7f7fa",
          "stroke": "#1890ff",
          "strokeWidth": 2.5,
          "strokeDashArray": null,
          "strokeLineCap": "butt",
          "strokeDashOffset": 0,
          "strokeLineJoin": "miter",
          "strokeUniform": true,
          "strokeMiterLimit": 4,
          "scaleX": 1,
          "scaleY": 1,
          "angle": 0,
          "flipX": false,
          "flipY": false,
          "opacity": 1,
          "shadow": {
            "color": "#cbe8ff",
            "blur": 8,
            "offsetX": 0,
            "offsetY": 2,
            "affectStroke": false,
            "nonScaling": false,
            "type": "shadow"
          },
          "visible": true,
          "backgroundColor": "",
          "fillRule": "nonzero",
          "paintFirst": "fill",
          "globalCompositeOperation": "source-over",
          "skewX": 0,
          "skewY": 0,
          "groupId": "4205b7dc-7a8e-44c3-bcde-623e2884f8b5",
          "objectType": "parkingGroup",
          "spotId": "71be7732-7630-4166-b29a-29ca97a02be0"
        },
        {
          "rx": 8,
          "ry": 8,
          "type": "Rect",
          "version": "6.6.5",
          "originX": "center",
          "originY": "center",
          "left": 275.6667,
          "top": 95,
          "width": 40,
          "height": 60,
          "fill": "#f7f7fa",
          "stroke": "#1890ff",
          "strokeWidth": 2.5,
          "strokeDashArray": null,
          "strokeLineCap": "butt",
          "strokeDashOffset": 0,
          "strokeLineJoin": "miter",
          "strokeUniform": true,
          "strokeMiterLimit": 4,
          "scaleX": 1,
          "scaleY": 1,
          "angle": 0,
          "flipX": false,
          "flipY": false,
          "opacity": 1,
          "shadow": {
            "color": "#cbe8ff",
            "blur": 8,
            "offsetX": 0,
            "offsetY": 2,
            "affectStroke": false,
            "nonScaling": false,
            "type": "shadow"
          },
          "visible": true,
          "backgroundColor": "",
          "fillRule": "nonzero",
          "paintFirst": "fill",
          "globalCompositeOperation": "source-over",
          "skewX": 0,
          "skewY": 0,
          "groupId": "4205b7dc-7a8e-44c3-bcde-623e2884f8b5",
          "objectType": "parkingGroup",
          "spotId": "7147ef24-0257-4a07-8a47-67220b1a53ef"
        },
        {
          "rx": 8,
          "ry": 8,
          "type": "Rect",
          "version": "6.6.5",
          "originX": "center",
          "originY": "center",
          "left": 353.5556,
          "top": 94.6667,
          "width": 40,
          "height": 60,
          "fill": "#f7f7fa",
          "stroke": "#1890ff",
          "strokeWidth": 2.5,
          "strokeDashArray": null,
          "strokeLineCap": "butt",
          "strokeDashOffset": 0,
          "strokeLineJoin": "miter",
          "strokeUniform": true,
          "strokeMiterLimit": 4,
          "scaleX": 1,
          "scaleY": 1,
          "angle": 0,
          "flipX": false,
          "flipY": false,
          "opacity": 1,
          "shadow": {
            "color": "#cbe8ff",
            "blur": 8,
            "offsetX": 0,
            "offsetY": 2,
            "affectStroke": false,
            "nonScaling": false,
            "type": "shadow"
          },
          "visible": true,
          "backgroundColor": "",
          "fillRule": "nonzero",
          "paintFirst": "fill",
          "globalCompositeOperation": "source-over",
          "skewX": 0,
          "skewY": 0,
          "groupId": "4205b7dc-7a8e-44c3-bcde-623e2884f8b5",
          "objectType": "parkingGroup",
          "spotId": "0e0af45a-badb-475f-9910-2a26fa33155b"
        },
        {
          "rx": 8,
          "ry": 8,
          "type": "Rect",
          "version": "6.6.5",
          "originX": "center",
          "originY": "center",
          "left": 431.4444,
          "top": 94.3333,
          "width": 40,
          "height": 60,
          "fill": "#f7f7fa",
          "stroke": "#1890ff",
          "strokeWidth": 2.5,
          "strokeDashArray": null,
          "strokeLineCap": "butt",
          "strokeDashOffset": 0,
          "strokeLineJoin": "miter",
          "strokeUniform": true,
          "strokeMiterLimit": 4,
          "scaleX": 1,
          "scaleY": 1,
          "angle": 0,
          "flipX": false,
          "flipY": false,
          "opacity": 1,
          "shadow": {
            "color": "#cbe8ff",
            "blur": 8,
            "offsetX": 0,
            "offsetY": 2,
            "affectStroke": false,
            "nonScaling": false,
            "type": "shadow"
          },
          "visible": true,
          "backgroundColor": "",
          "fillRule": "nonzero",
          "paintFirst": "fill",
          "globalCompositeOperation": "source-over",
          "skewX": 0,
          "skewY": 0,
          "groupId": "4205b7dc-7a8e-44c3-bcde-623e2884f8b5",
          "objectType": "parkingGroup",
          "spotId": "01dbeea6-2c6f-4fd9-abd7-b3d268b1db54"
        },
        {
          "rx": 8,
          "ry": 8,
          "type": "Rect",
          "version": "6.6.5",
          "originX": "center",
          "originY": "center",
          "left": 509.3333,
          "top": 94,
          "width": 40,
          "height": 60,
          "fill": "#f7f7fa",
          "stroke": "#1890ff",
          "strokeWidth": 2.5,
          "strokeDashArray": null,
          "strokeLineCap": "butt",
          "strokeDashOffset": 0,
          "strokeLineJoin": "miter",
          "strokeUniform": true,
          "strokeMiterLimit": 4,
          "scaleX": 1,
          "scaleY": 1,
          "angle": 0,
          "flipX": false,
          "flipY": false,
          "opacity": 1,
          "shadow": {
            "color": "#cbe8ff",
            "blur": 8,
            "offsetX": 0,
            "offsetY": 2,
            "affectStroke": false,
            "nonScaling": false,
            "type": "shadow"
          },
          "visible": true,
          "backgroundColor": "",
          "fillRule": "nonzero",
          "paintFirst": "fill",
          "globalCompositeOperation": "source-over",
          "skewX": 0,
          "skewY": 0,
          "groupId": "4205b7dc-7a8e-44c3-bcde-623e2884f8b5",
          "objectType": "parkingGroup",
          "spotId": "9f23340e-ce6a-4831-b2b4-a669ca66ee99"
        },
        {
          "rx": 8,
          "ry": 8,
          "type": "Rect",
          "version": "6.6.5",
          "originX": "center",
          "originY": "center",
          "left": 587.2222,
          "top": 93.6667,
          "width": 40,
          "height": 60,
          "fill": "#f7f7fa",
          "stroke": "#1890ff",
          "strokeWidth": 2.5,
          "strokeDashArray": null,
          "strokeLineCap": "butt",
          "strokeDashOffset": 0,
          "strokeLineJoin": "miter",
          "strokeUniform": true,
          "strokeMiterLimit": 4,
          "scaleX": 1,
          "scaleY": 1,
          "angle": 0,
          "flipX": false,
          "flipY": false,
          "opacity": 1,
          "shadow": {
            "color": "#cbe8ff",
            "blur": 8,
            "offsetX": 0,
            "offsetY": 2,
            "affectStroke": false,
            "nonScaling": false,
            "type": "shadow"
          },
          "visible": true,
          "backgroundColor": "",
          "fillRule": "nonzero",
          "paintFirst": "fill",
          "globalCompositeOperation": "source-over",
          "skewX": 0,
          "skewY": 0,
          "groupId": "4205b7dc-7a8e-44c3-bcde-623e2884f8b5",
          "objectType": "parkingGroup",
          "spotId": "770e3cd4-1c9b-44fb-825d-bcff9f4113f7"
        },
        {
          "rx": 8,
          "ry": 8,
          "type": "Rect",
          "version": "6.6.5",
          "originX": "center",
          "originY": "center",
          "left": 665.1111,
          "top": 93.3333,
          "width": 40,
          "height": 60,
          "fill": "#f7f7fa",
          "stroke": "#1890ff",
          "strokeWidth": 2.5,
          "strokeDashArray": null,
          "strokeLineCap": "butt",
          "strokeDashOffset": 0,
          "strokeLineJoin": "miter",
          "strokeUniform": true,
          "strokeMiterLimit": 4,
          "scaleX": 1,
          "scaleY": 1,
          "angle": 0,
          "flipX": false,
          "flipY": false,
          "opacity": 1,
          "shadow": {
            "color": "#cbe8ff",
            "blur": 8,
            "offsetX": 0,
            "offsetY": 2,
            "affectStroke": false,
            "nonScaling": false,
            "type": "shadow"
          },
          "visible": true,
          "backgroundColor": "",
          "fillRule": "nonzero",
          "paintFirst": "fill",
          "globalCompositeOperation": "source-over",
          "skewX": 0,
          "skewY": 0,
          "groupId": "4205b7dc-7a8e-44c3-bcde-623e2884f8b5",
          "objectType": "parkingGroup",
          "spotId": "7454eef6-d1c7-4bb2-8a84-a5a5ad083e65"
        }
      ],
      "spotCount": 8,
      "spotSize": {
        "width": 40,
        "height": 60
      },
      "spotAngle": 0
    },
    {
      "id": "7b1ee9cf-ed8e-404a-be5e-6d522982b300",
      "line": {
        "type": "Line",
        "version": "6.6.5",
        "originX": "left",
        "originY": "top",
        "left": 714,
        "top": 105,
        "width": 10,
        "height": 600,
        "fill": "rgb(0,0,0)",
        "stroke": "#1976d2",
        "strokeWidth": 4,
        "strokeDashArray": null,
        "strokeLineCap": "round",
        "strokeDashOffset": 0,
        "strokeLineJoin": "miter",
        "strokeUniform": false,
        "strokeMiterLimit": 4,
        "scaleX": 1,
        "scaleY": 1,
        "angle": 0,
        "flipX": false,
        "flipY": false,
        "opacity": 1,
        "shadow": {
          "color": "#a2c8f7",
          "blur": 8,
          "offsetX": 0,
          "offsetY": 2,
          "affectStroke": false,
          "nonScaling": false,
          "type": "shadow"
        },
        "visible": true,
        "backgroundColor": "",
        "fillRule": "nonzero",
        "paintFirst": "fill",
        "globalCompositeOperation": "source-over",
        "skewX": 0,
        "skewY": 0,
        "objectId": "7b1ee9cf-ed8e-404a-be5e-6d522982b300",
        "groupId": "7b1ee9cf-ed8e-404a-be5e-6d522982b300",
        "objectType": "parkingGroup",
        "x1": 5,
        "x2": -5,
        "y1": 300,
        "y2": -300
      },
      "spots": [
        {
          "rx": 8,
          "ry": 8,
          "type": "Rect",
          "version": "6.6.5",
          "originX": "center",
          "originY": "center",
          "left": 724.5714,
          "top": 621.2857,
          "width": 40,
          "height": 60,
          "fill": "#f7f7fa",
          "stroke": "#1890ff",
          "strokeWidth": 2.5,
          "strokeDashArray": null,
          "strokeLineCap": "butt",
          "strokeDashOffset": 0,
          "strokeLineJoin": "miter",
          "strokeUniform": true,
          "strokeMiterLimit": 4,
          "scaleX": 1,
          "scaleY": 1,
          "angle": 0,
          "flipX": false,
          "flipY": false,
          "opacity": 1,
          "shadow": {
            "color": "#cbe8ff",
            "blur": 8,
            "offsetX": 0,
            "offsetY": 2,
            "affectStroke": false,
            "nonScaling": false,
            "type": "shadow"
          },
          "visible": true,
          "backgroundColor": "",
          "fillRule": "nonzero",
          "paintFirst": "fill",
          "globalCompositeOperation": "source-over",
          "skewX": 0,
          "skewY": 0,
          "groupId": "7b1ee9cf-ed8e-404a-be5e-6d522982b300",
          "objectType": "parkingGroup",
          "spotId": "70ebeb06-7310-4922-b65a-3c55c75079cf"
        },
        {
          "rx": 8,
          "ry": 8,
          "type": "Rect",
          "version": "6.6.5",
          "originX": "center",
          "originY": "center",
          "left": 723.1429,
          "top": 535.5714,
          "width": 40,
          "height": 60,
          "fill": "#f7f7fa",
          "stroke": "#1890ff",
          "strokeWidth": 2.5,
          "strokeDashArray": null,
          "strokeLineCap": "butt",
          "strokeDashOffset": 0,
          "strokeLineJoin": "miter",
          "strokeUniform": true,
          "strokeMiterLimit": 4,
          "scaleX": 1,
          "scaleY": 1,
          "angle": 0,
          "flipX": false,
          "flipY": false,
          "opacity": 1,
          "shadow": {
            "color": "#cbe8ff",
            "blur": 8,
            "offsetX": 0,
            "offsetY": 2,
            "affectStroke": false,
            "nonScaling": false,
            "type": "shadow"
          },
          "visible": true,
          "backgroundColor": "",
          "fillRule": "nonzero",
          "paintFirst": "fill",
          "globalCompositeOperation": "source-over",
          "skewX": 0,
          "skewY": 0,
          "groupId": "7b1ee9cf-ed8e-404a-be5e-6d522982b300",
          "objectType": "parkingGroup",
          "spotId": "9eaf95f6-15bc-4905-a000-e87577b4e79d"
        },
        {
          "rx": 8,
          "ry": 8,
          "type": "Rect",
          "version": "6.6.5",
          "originX": "center",
          "originY": "center",
          "left": 721.7143,
          "top": 449.8571,
          "width": 40,
          "height": 60,
          "fill": "#f7f7fa",
          "stroke": "#1890ff",
          "strokeWidth": 2.5,
          "strokeDashArray": null,
          "strokeLineCap": "butt",
          "strokeDashOffset": 0,
          "strokeLineJoin": "miter",
          "strokeUniform": true,
          "strokeMiterLimit": 4,
          "scaleX": 1,
          "scaleY": 1,
          "angle": 0,
          "flipX": false,
          "flipY": false,
          "opacity": 1,
          "shadow": {
            "color": "#cbe8ff",
            "blur": 8,
            "offsetX": 0,
            "offsetY": 2,
            "affectStroke": false,
            "nonScaling": false,
            "type": "shadow"
          },
          "visible": true,
          "backgroundColor": "",
          "fillRule": "nonzero",
          "paintFirst": "fill",
          "globalCompositeOperation": "source-over",
          "skewX": 0,
          "skewY": 0,
          "groupId": "7b1ee9cf-ed8e-404a-be5e-6d522982b300",
          "objectType": "parkingGroup",
          "spotId": "0472d305-1178-4d23-9260-ff1f0c765ee5"
        },
        {
          "rx": 8,
          "ry": 8,
          "type": "Rect",
          "version": "6.6.5",
          "originX": "center",
          "originY": "center",
          "left": 720.2857,
          "top": 364.1429,
          "width": 40,
          "height": 60,
          "fill": "#f7f7fa",
          "stroke": "#1890ff",
          "strokeWidth": 2.5,
          "strokeDashArray": null,
          "strokeLineCap": "butt",
          "strokeDashOffset": 0,
          "strokeLineJoin": "miter",
          "strokeUniform": true,
          "strokeMiterLimit": 4,
          "scaleX": 1,
          "scaleY": 1,
          "angle": 0,
          "flipX": false,
          "flipY": false,
          "opacity": 1,
          "shadow": {
            "color": "#cbe8ff",
            "blur": 8,
            "offsetX": 0,
            "offsetY": 2,
            "affectStroke": false,
            "nonScaling": false,
            "type": "shadow"
          },
          "visible": true,
          "backgroundColor": "",
          "fillRule": "nonzero",
          "paintFirst": "fill",
          "globalCompositeOperation": "source-over",
          "skewX": 0,
          "skewY": 0,
          "groupId": "7b1ee9cf-ed8e-404a-be5e-6d522982b300",
          "objectType": "parkingGroup",
          "spotId": "4bec3f40-a34b-45be-ba87-a9210062a398"
        },
        {
          "rx": 8,
          "ry": 8,
          "type": "Rect",
          "version": "6.6.5",
          "originX": "center",
          "originY": "center",
          "left": 718.8571,
          "top": 278.4286,
          "width": 40,
          "height": 60,
          "fill": "#f7f7fa",
          "stroke": "#1890ff",
          "strokeWidth": 2.5,
          "strokeDashArray": null,
          "strokeLineCap": "butt",
          "strokeDashOffset": 0,
          "strokeLineJoin": "miter",
          "strokeUniform": true,
          "strokeMiterLimit": 4,
          "scaleX": 1,
          "scaleY": 1,
          "angle": 0,
          "flipX": false,
          "flipY": false,
          "opacity": 1,
          "shadow": {
            "color": "#cbe8ff",
            "blur": 8,
            "offsetX": 0,
            "offsetY": 2,
            "affectStroke": false,
            "nonScaling": false,
            "type": "shadow"
          },
          "visible": true,
          "backgroundColor": "",
          "fillRule": "nonzero",
          "paintFirst": "fill",
          "globalCompositeOperation": "source-over",
          "skewX": 0,
          "skewY": 0,
          "groupId": "7b1ee9cf-ed8e-404a-be5e-6d522982b300",
          "objectType": "parkingGroup",
          "spotId": "97466e4c-cca6-474e-b0d6-f60be9390ade"
        },
        {
          "rx": 8,
          "ry": 8,
          "type": "Rect",
          "version": "6.6.5",
          "originX": "center",
          "originY": "center",
          "left": 717.4286,
          "top": 192.7143,
          "width": 40,
          "height": 60,
          "fill": "#f7f7fa",
          "stroke": "#1890ff",
          "strokeWidth": 2.5,
          "strokeDashArray": null,
          "strokeLineCap": "butt",
          "strokeDashOffset": 0,
          "strokeLineJoin": "miter",
          "strokeUniform": true,
          "strokeMiterLimit": 4,
          "scaleX": 1,
          "scaleY": 1,
          "angle": 0,
          "flipX": false,
          "flipY": false,
          "opacity": 1,
          "shadow": {
            "color": "#cbe8ff",
            "blur": 8,
            "offsetX": 0,
            "offsetY": 2,
            "affectStroke": false,
            "nonScaling": false,
            "type": "shadow"
          },
          "visible": true,
          "backgroundColor": "",
          "fillRule": "nonzero",
          "paintFirst": "fill",
          "globalCompositeOperation": "source-over",
          "skewX": 0,
          "skewY": 0,
          "groupId": "7b1ee9cf-ed8e-404a-be5e-6d522982b300",
          "objectType": "parkingGroup",
          "spotId": "7f9c5227-adf5-44a9-aabb-bbdcfcfdd48b"
        }
      ],
      "spotCount": 6,
      "spotSize": {
        "width": 40,
        "height": 60
      },
      "spotAngle": 0
    },
    {
      "id": "0e425645-8123-4fca-ae83-cfd48a3e9d4f",
      "line": {
        "type": "Line",
        "version": "6.6.5",
        "originX": "left",
        "originY": "top",
        "left": 87,
        "top": 242,
        "width": 322,
        "height": 459,
        "fill": "rgb(0,0,0)",
        "stroke": "#1976d2",
        "strokeWidth": 4,
        "strokeDashArray": null,
        "strokeLineCap": "round",
        "strokeDashOffset": 0,
        "strokeLineJoin": "miter",
        "strokeUniform": false,
        "strokeMiterLimit": 4,
        "scaleX": 1,
        "scaleY": 1,
        "angle": 0,
        "flipX": false,
        "flipY": false,
        "opacity": 1,
        "shadow": {
          "color": "#a2c8f7",
          "blur": 8,
          "offsetX": 0,
          "offsetY": 2,
          "affectStroke": false,
          "nonScaling": false,
          "type": "shadow"
        },
        "visible": true,
        "backgroundColor": "",
        "fillRule": "nonzero",
        "paintFirst": "fill",
        "globalCompositeOperation": "source-over",
        "skewX": 0,
        "skewY": 0,
        "objectId": "0e425645-8123-4fca-ae83-cfd48a3e9d4f",
        "groupId": "0e425645-8123-4fca-ae83-cfd48a3e9d4f",
        "objectType": "parkingGroup",
        "x1": -161,
        "x2": 161,
        "y1": -229.5,
        "y2": 229.5
      },
      "spots": [
        {
          "rx": 8,
          "ry": 8,
          "type": "Rect",
          "version": "6.6.5",
          "originX": "center",
          "originY": "center",
          "left": 142.6667,
          "top": 320.5,
          "width": 40,
          "height": 60,
          "fill": "#f7f7fa",
          "stroke": "#1890ff",
          "strokeWidth": 2.5,
          "strokeDashArray": null,
          "strokeLineCap": "butt",
          "strokeDashOffset": 0,
          "strokeLineJoin": "miter",
          "strokeUniform": true,
          "strokeMiterLimit": 4,
          "scaleX": 1,
          "scaleY": 1,
          "angle": -35,
          "flipX": false,
          "flipY": false,
          "opacity": 1,
          "shadow": {
            "color": "#cbe8ff",
            "blur": 8,
            "offsetX": 0,
            "offsetY": 2,
            "affectStroke": false,
            "nonScaling": false,
            "type": "shadow"
          },
          "visible": true,
          "backgroundColor": "",
          "fillRule": "nonzero",
          "paintFirst": "fill",
          "globalCompositeOperation": "source-over",
          "skewX": 0,
          "skewY": 0,
          "groupId": "0e425645-8123-4fca-ae83-cfd48a3e9d4f",
          "objectType": "parkingGroup",
          "spotId": "968ce770-6567-4e1e-b844-fcfec99d0e00"
        },
        {
          "rx": 8,
          "ry": 8,
          "type": "Rect",
          "version": "6.6.5",
          "originX": "center",
          "originY": "center",
          "left": 196.3333,
          "top": 397,
          "width": 40,
          "height": 60,
          "fill": "#f7f7fa",
          "stroke": "#1890ff",
          "strokeWidth": 2.5,
          "strokeDashArray": null,
          "strokeLineCap": "butt",
          "strokeDashOffset": 0,
          "strokeLineJoin": "miter",
          "strokeUniform": true,
          "strokeMiterLimit": 4,
          "scaleX": 1,
          "scaleY": 1,
          "angle": -35,
          "flipX": false,
          "flipY": false,
          "opacity": 1,
          "shadow": {
            "color": "#cbe8ff",
            "blur": 8,
            "offsetX": 0,
            "offsetY": 2,
            "affectStroke": false,
            "nonScaling": false,
            "type": "shadow"
          },
          "visible": true,
          "backgroundColor": "",
          "fillRule": "nonzero",
          "paintFirst": "fill",
          "globalCompositeOperation": "source-over",
          "skewX": 0,
          "skewY": 0,
          "groupId": "0e425645-8123-4fca-ae83-cfd48a3e9d4f",
          "objectType": "parkingGroup",
          "spotId": "118a913d-5779-4128-bafb-ca018e07977b"
        },
        {
          "rx": 8,
          "ry": 8,
          "type": "Rect",
          "version": "6.6.5",
          "originX": "center",
          "originY": "center",
          "left": 250,
          "top": 473.5,
          "width": 40,
          "height": 60,
          "fill": "#f7f7fa",
          "stroke": "#1890ff",
          "strokeWidth": 2.5,
          "strokeDashArray": null,
          "strokeLineCap": "butt",
          "strokeDashOffset": 0,
          "strokeLineJoin": "miter",
          "strokeUniform": true,
          "strokeMiterLimit": 4,
          "scaleX": 1,
          "scaleY": 1,
          "angle": -35,
          "flipX": false,
          "flipY": false,
          "opacity": 1,
          "shadow": {
            "color": "#cbe8ff",
            "blur": 8,
            "offsetX": 0,
            "offsetY": 2,
            "affectStroke": false,
            "nonScaling": false,
            "type": "shadow"
          },
          "visible": true,
          "backgroundColor": "",
          "fillRule": "nonzero",
          "paintFirst": "fill",
          "globalCompositeOperation": "source-over",
          "skewX": 0,
          "skewY": 0,
          "groupId": "0e425645-8123-4fca-ae83-cfd48a3e9d4f",
          "objectType": "parkingGroup",
          "spotId": "28d43baf-9be9-4b7c-9b86-b1fab5adae26"
        },
        {
          "rx": 8,
          "ry": 8,
          "type": "Rect",
          "version": "6.6.5",
          "originX": "center",
          "originY": "center",
          "left": 303.6667,
          "top": 550,
          "width": 40,
          "height": 60,
          "fill": "#f7f7fa",
          "stroke": "#1890ff",
          "strokeWidth": 2.5,
          "strokeDashArray": null,
          "strokeLineCap": "butt",
          "strokeDashOffset": 0,
          "strokeLineJoin": "miter",
          "strokeUniform": true,
          "strokeMiterLimit": 4,
          "scaleX": 1,
          "scaleY": 1,
          "angle": -35,
          "flipX": false,
          "flipY": false,
          "opacity": 1,
          "shadow": {
            "color": "#cbe8ff",
            "blur": 8,
            "offsetX": 0,
            "offsetY": 2,
            "affectStroke": false,
            "nonScaling": false,
            "type": "shadow"
          },
          "visible": true,
          "backgroundColor": "",
          "fillRule": "nonzero",
          "paintFirst": "fill",
          "globalCompositeOperation": "source-over",
          "skewX": 0,
          "skewY": 0,
          "groupId": "0e425645-8123-4fca-ae83-cfd48a3e9d4f",
          "objectType": "parkingGroup",
          "spotId": "8919f27c-6228-4ac4-9fbf-83c467a9f482"
        },
        {
          "rx": 8,
          "ry": 8,
          "type": "Rect",
          "version": "6.6.5",
          "originX": "center",
          "originY": "center",
          "left": 357.3333,
          "top": 626.5,
          "width": 40,
          "height": 60,
          "fill": "#f7f7fa",
          "stroke": "#1890ff",
          "strokeWidth": 2.5,
          "strokeDashArray": null,
          "strokeLineCap": "butt",
          "strokeDashOffset": 0,
          "strokeLineJoin": "miter",
          "strokeUniform": true,
          "strokeMiterLimit": 4,
          "scaleX": 1,
          "scaleY": 1,
          "angle": -35,
          "flipX": false,
          "flipY": false,
          "opacity": 1,
          "shadow": {
            "color": "#cbe8ff",
            "blur": 8,
            "offsetX": 0,
            "offsetY": 2,
            "affectStroke": false,
            "nonScaling": false,
            "type": "shadow"
          },
          "visible": true,
          "backgroundColor": "",
          "fillRule": "nonzero",
          "paintFirst": "fill",
          "globalCompositeOperation": "source-over",
          "skewX": 0,
          "skewY": 0,
          "groupId": "0e425645-8123-4fca-ae83-cfd48a3e9d4f",
          "objectType": "parkingGroup",
          "spotId": "1bcab04a-8e27-432f-ad7c-c1c156c7fd5f"
        }
      ],
      "spotCount": 5,
      "spotSize": {
        "width": 40,
        "height": 60
      },
      "spotAngle": -35
    }
  ]
}

82d3d324-6e40-4e46-b3b3-3acd0dd0c359
71be7732-7630-4166-b29a-29ca97a02be0
7147ef24-0257-4a07-8a47-67220b1a53ef
0e0af45a-badb-475f-9910-2a26fa33155b
01dbeea6-2c6f-4fd9-abd7-b3d268b1db54
9f23340e-ce6a-4831-b2b4-a669ca66ee99
770e3cd4-1c9b-44fb-825d-bcff9f4113f7
7454eef6-d1c7-4bb2-8a84-a5a5ad083e65
70ebeb06-7310-4922-b65a-3c55c75079cf
9eaf95f6-15bc-4905-a000-e87577b4e79d
0472d305-1178-4d23-9260-ff1f0c765ee5
4bec3f40-a34b-45be-ba87-a9210062a398
97466e4c-cca6-474e-b0d6-f60be9390ade
7f9c5227-adf5-44a9-aabb-bbdcfcfdd48b
968ce770-6567-4e1e-b844-fcfec99d0e00
118a913d-5779-4128-bafb-ca018e07977b
28d43baf-9be9-4b7c-9b86-b1fab5adae26
8919f27c-6228-4ac4-9fbf-83c467a9f482
1bcab04a-8e27-432f-ad7c-c1c156c7fd5f